LICENSE.md
MANIFEST.in
README.md
__init__.py
requirements.txt
setup.cfg
setup.py
python_magic_win64.egg-info/PKG-INFO
python_magic_win64.egg-info/SOURCES.txt
python_magic_win64.egg-info/dependency_links.txt
python_magic_win64.egg-info/requires.txt
python_magic_win64.egg-info/top_level.txt
winmagic/__init__.py
winmagic/nscaife/COPYING.file
winmagic/nscaife/COPYING.libgnurx
winmagic/nscaife/libgnurx-0.dll
winmagic/nscaife/magic.mgc
winmagic/nscaife/magic1.dll